{
  "id": 7364959,
  "url": "https://www.riteaid.com/pharmacy/covid-qualifier",
  "city": "Minersville",
  "name": "Rite Aid",
  "state": "PA",
  "address": "44 Kings Village",
  "provider": "rite_aid",
  "time_zone": "America/New_York",
  "postal_code": "17954",
  "appointments": [],
  "provider_brand": "rite_aid",
  "carries_vaccine": true,
  "provider_brand_name": "Rite Aid",
  "provider_location_id": "2693",
  "appointments_available": true,
  "appointments_last_fetched": "2021-03-19T03:53:53.514+00:00"
}
{
  "id": 7365002,
  "url": "https://www.riteaid.com/pharmacy/covid-qualifier",
  "city": "Berwick",
  "name": "Rite Aid",
  "state": "PA",
  "address": "400 West Second Street",
  "provider": "rite_aid",
  "time_zone": "America/New_York",
  "postal_code": "18603",
  "appointments": [],
  "provider_brand": "rite_aid",
  "carries_vaccine": true,
  "provider_brand_name": "Rite Aid",
  "provider_location_id": "11073",
  "appointments_available": true,
  "appointments_last_fetched": "2021-03-19T03:53:07.273+00:00"
}
{
  "id": 7364209,
  "url": "https://www.riteaid.com/pharmacy/covid-qualifier",
  "city": "Beaver",
  "name": "Rite Aid",
  "state": "PA",
  "address": "1799 Third Street",
  "provider": "rite_aid",
  "time_zone": "America/New_York",
  "postal_code": "15009",
  "appointments": [],
  "provider_brand": "rite_aid",
  "carries_vaccine": true,
  "provider_brand_name": "Rite Aid",
  "provider_location_id": "2277",
  "appointments_available": true,
  "appointments_last_fetched": "2021-03-19T03:53:00.703+00:00"
}
{
  "id": 7365028,
  "url": "https://www.riteaid.com/pharmacy/covid-qualifier",
  "city": "Pottstown",
  "name": "Rite Aid",
  "state": "PA",
  "address": "1140 Town Square Rd",
  "provider": "rite_aid",
  "time_zone": "America/New_York",
  "postal_code": "19465",
  "appointments": [],
  "provider_brand": "rite_aid",
  "carries_vaccine": true,
  "provider_brand_name": "Rite Aid",
  "provider_location_id": "11166",
  "appointments_available": true,
  "appointments_last_fetched": "2021-03-19T03:53:00.356+00:00"
}
{
  "id": 7351250,
  "url": "https://www.riteaid.com/pharmacy/covid-qualifier",
  "city": "Hamburg",
  "name": "Rite Aid",
  "state": "PA",
  "address": "807 South 4th Street",
  "provider": "rite_aid",
  "time_zone": "America/New_York",
  "postal_code": "19526",
  "appointments": [],
  "provider_brand": "rite_aid",
  "carries_vaccine": true,
  "provider_brand_name": "Rite Aid",
  "provider_location_id": "3425",
  "appointments_available": true,
  "appointments_last_fetched": "2021-03-19T03:52:29.758+00:00"
}
{
  "id": 7364221,
  "url": "https://www.riteaid.com/pharmacy/covid-qualifier",
  "city": "Monroeville",
  "name": "Rite Aid",
  "state": "PA",
  "address": "4534 Broadway Blvd.",
  "provider": "rite_aid",
  "time_zone": "America/New_York",
  "postal_code": "15146",
  "appointments": [],
  "provider_brand": "rite_aid",
  "carries_vaccine": true,
  "provider_brand_name": "Rite Aid",
  "provider_location_id": "10919",
  "appointments_available": true,
  "appointments_last_fetched": "2021-03-19T03:52:28.46+00:00"
}
{
  "id": 7364952,
  "url": "https://www.riteaid.com/pharmacy/covid-qualifier",
  "city": "Spring Grove",
  "name": "Rite Aid",
  "state": "PA",
  "address": "2067 Route 116",
  "provider": "rite_aid",
  "time_zone": "America/New_York",
  "postal_code": "17362",
  "appointments": [],
  "provider_brand": "rite_aid",
  "carries_vaccine": true,
  "provider_brand_name": "Rite Aid",
  "provider_location_id": "1902",
  "appointments_available": true,
  "appointments_last_fetched": "2021-03-19T03:52:25.848+00:00"
}
{
  "id": 7364233,
  "url": "https://www.riteaid.com/pharmacy/covid-qualifier",
  "city": "Uniontown",
  "name": "Rite Aid",
  "state": "PA",
  "address": "262 Connellsville Street",
  "provider": "rite_aid",
  "time_zone": "America/New_York",
  "postal_code": "15401",
  "appointments": [],
  "provider_brand": "rite_aid",
  "carries_vaccine": true,
  "provider_brand_name": "Rite Aid",
  "provider_location_id": "1963",
  "appointments_available": true,
  "appointments_last_fetched": "2021-03-19T03:52:02.726+00:00"
}
{
  "id": 7364267,
  "url": "https://www.riteaid.com/pharmacy/covid-qualifier",
  "city": "Kittanning",
  "name": "Rite Aid",
  "state": "PA",
  "address": "165 Butler Road",
  "provider": "rite_aid",
  "time_zone": "America/New_York",
  "postal_code": "16201",
  "appointments": [],
  "provider_brand": "rite_aid",
  "carries_vaccine": true,
  "provider_brand_name": "Rite Aid",
  "provider_location_id": "10998",
  "appointments_available": true,
  "appointments_last_fetched": "2021-03-19T03:51:57.262+00:00"
}
{
  "id": 7351206,
  "url": "https://www.riteaid.com/pharmacy/covid-qualifier",
  "city": "Wellsboro",
  "name": "Rite Aid",
  "state": "PA",
  "address": "24 East Avenue",
  "provider": "rite_aid",
  "time_zone": "America/New_York",
  "postal_code": "16901",
  "appointments": [],
  "provider_brand": "rite_aid",
  "carries_vaccine": true,
  "provider_brand_name": "Rite Aid",
  "provider_location_id": "11016",
  "appointments_available": true,
  "appointments_last_fetched": "2021-03-19T03:51:28.276+00:00"
}
{
  "id": 7364923,
  "url": "https://www.riteaid.com/pharmacy/covid-qualifier",
  "city": "Cleona",
  "name": "Rite Aid",
  "state": "PA",
  "address": "469 West Penn Avenue",
  "provider": "rite_aid",
  "time_zone": "America/New_York",
  "postal_code": "17042",
  "appointments": [],
  "provider_brand": "rite_aid",
  "carries_vaccine": true,
  "provider_brand_name": "Rite Aid",
  "provider_location_id": "11021",
  "appointments_available": true,
  "appointments_last_fetched": "2021-03-19T03:51:07.096+00:00"
}
{
  "id": 7364226,
  "url": "https://www.riteaid.com/pharmacy/covid-qualifier",
  "city": "Grindstone",
  "name": "Rite Aid",
  "state": "PA",
  "address": "6039 National Pike",
  "provider": "rite_aid",
  "time_zone": "America/New_York",
  "postal_code": "15442",
  "appointments": [],
  "provider_brand": "rite_aid",
  "carries_vaccine": true,
  "provider_brand_name": "Rite Aid",
  "provider_location_id": "3443",
  "appointments_available": true,
  "appointments_last_fetched": "2021-03-19T03:50:20.401+00:00"
}
{
  "id": 7503924,
  "url": "https://www.riteaid.com/pharmacy/covid-qualifier",
  "city": "Munhall",
  "name": "Rite Aid",
  "state": "PA",
  "address": "100 William Marks Drive",
  "provider": "rite_aid",
  "time_zone": "America/New_York",
  "postal_code": "15120",
  "appointments": [],
  "provider_brand": "rite_aid",
  "carries_vaccine": true,
  "provider_brand_name": "Rite Aid",
  "provider_location_id": "4682",
  "appointments_available": true,
  "appointments_last_fetched": "2021-03-19T03:50:18.693+00:00"
}
{
  "id": 7503934,
  "url": "https://www.riteaid.com/pharmacy/covid-qualifier",
  "city": "McKees Rocks",
  "name": "Rite Aid",
  "state": "PA",
  "address": "155 Chartiers Avenue",
  "provider": "rite_aid",
  "time_zone": "America/New_York",
  "postal_code": "15136",
  "appointments": [],
  "provider_brand": "rite_aid",
  "carries_vaccine": true,
  "provider_brand_name": "Rite Aid",
  "provider_location_id": "3527",
  "appointments_available": true,
  "appointments_last_fetched": "2021-03-19T03:50:16.564+00:00"
}
{
  "id": 7351193,
  "url": "https://www.riteaid.com/pharmacy/covid-qualifier",
  "city": "Kane",
  "name": "Rite Aid",
  "state": "PA",
  "address": "521 North Fraley Street",
  "provider": "rite_aid",
  "time_zone": "America/New_York",
  "postal_code": "16735",
  "appointments": [],
  "provider_brand": "rite_aid",
  "carries_vaccine": true,
  "provider_brand_name": "Rite Aid",
  "provider_location_id": "1406",
  "appointments_available": true,
  "appointments_last_fetched": "2021-03-19T03:50:05.049+00:00"
}
{
  "id": 7508768,
  "url": "https://www.riteaid.com/pharmacy/covid-qualifier",
  "city": "Lancaster",
  "name": "Rite Aid",
  "state": "PA",
  "address": "825A East Chestnut Street",
  "provider": "rite_aid",
  "time_zone": "America/New_York",
  "postal_code": "17602",
  "appointments": [],
  "provider_brand": "rite_aid",
  "carries_vaccine": true,
  "provider_brand_name": "Rite Aid",
  "provider_location_id": "4684",
  "appointments_available": true,
  "appointments_last_fetched": "2021-03-19T03:50:03.912+00:00"
}
{
  "id": 7364274,
  "url": "https://www.riteaid.com/pharmacy/covid-qualifier",
  "city": "Lower Burrell",
  "name": "Rite Aid",
  "state": "PA",
  "address": "3200 Oregon Drive",
  "provider": "rite_aid",
  "time_zone": "America/New_York",
  "postal_code": "15068",
  "appointments": [],
  "provider_brand": "rite_aid",
  "carries_vaccine": true,
  "provider_brand_name": "Rite Aid",
  "provider_location_id": "10899",
  "appointments_available": true,
  "appointments_last_fetched": "2021-03-19T03:50:02.745+00:00"
}
{
  "id": 7351169,
  "url": "https://www.riteaid.com/pharmacy/covid-qualifier",
  "city": "Johnstown",
  "name": "Rite Aid",
  "state": "PA",
  "address": "1501 Scalp Avenue",
  "provider": "rite_aid",
  "time_zone": "America/New_York",
  "postal_code": "15904",
  "appointments": [],
  "provider_brand": "rite_aid",
  "carries_vaccine": true,
  "provider_brand_name": "Rite Aid",
  "provider_location_id": "10979",
  "appointments_available": true,
  "appointments_last_fetched": "2021-03-19T03:50:02.51+00:00"
}
{
  "id": 7351175,
  "url": "https://www.riteaid.com/pharmacy/covid-qualifier",
  "city": "Everett",
  "name": "Rite Aid",
  "state": "PA",
  "address": "211 East Main Street",
  "provider": "rite_aid",
  "time_zone": "America/New_York",
  "postal_code": "15537",
  "appointments": [],
  "provider_brand": "rite_aid",
  "carries_vaccine": true,
  "provider_brand_name": "Rite Aid",
  "provider_location_id": "1429",
  "appointments_available": true,
  "appointments_last_fetched": "2021-03-19T03:50:02.182+00:00"
}
{
  "id": 7351200,
  "url": "https://www.riteaid.com/pharmacy/covid-qualifier",
  "city": "Punxsutawney",
  "name": "Rite Aid",
  "state": "PA",
  "address": "201 West Mahoning Street",
  "provider": "rite_aid",
  "time_zone": "America/New_York",
  "postal_code": "15767",
  "appointments": [],
  "provider_brand": "rite_aid",
  "carries_vaccine": true,
  "provider_brand_name": "Rite Aid",
  "provider_location_id": "10975",
  "appointments_available": true,
  "appointments_last_fetched": "2021-03-19T03:50:01.688+00:00"
}
{
  "id": 7364966,
  "url": "https://www.riteaid.com/pharmacy/covid-qualifier",
  "city": "Tamaqua",
  "name": "Rite Aid",
  "state": "PA",
  "address": "205 Center Street",
  "provider": "rite_aid",
  "time_zone": "America/New_York",
  "postal_code": "18252",
  "appointments": [],
  "provider_brand": "rite_aid",
  "carries_vaccine": true,
  "provider_brand_name": "Rite Aid",
  "provider_location_id": "11060",
  "appointments_available": true,
  "appointments_last_fetched": "2021-03-19T03:49:36.072+00:00"
}
{
  "id": 7351181,
  "url": "https://www.riteaid.com/pharmacy/covid-qualifier",
  "city": "Oil City",
  "name": "Rite Aid",
  "state": "PA",
  "address": "508 East Second Street",
  "provider": "rite_aid",
  "time_zone": "America/New_York",
  "postal_code": "16301",
  "appointments": [],
  "provider_brand": "rite_aid",
  "carries_vaccine": true,
  "provider_brand_name": "Rite Aid",
  "provider_location_id": "1496",
  "appointments_available": true,
  "appointments_last_fetched": "2021-03-19T03:49:22.958+00:00"
}
{
  "id": 7351168,
  "url": "https://www.riteaid.com/pharmacy/covid-qualifier",
  "city": "Windber",
  "name": "Rite Aid",
  "state": "PA",
  "address": "1516 Jefferson Avenue",
  "provider": "rite_aid",
  "time_zone": "America/New_York",
  "postal_code": "15963",
  "appointments": [],
  "provider_brand": "rite_aid",
  "carries_vaccine": true,
  "provider_brand_name": "Rite Aid",
  "provider_location_id": "1780",
  "appointments_available": true,
  "appointments_last_fetched": "2021-03-19T03:49:14.981+00:00"
}
